LICENSE
MANIFEST.in
README.rst
requirements.txt
setup.py
finance/__init__.py
finance/__main__.py
finance/exceptions.py
finance/fetchers.py
finance/importers.py
finance/models.py
finance/utils.py
finance/ext/__init__.py
finance/ext/dart.py
finance/ext/datareader.py
finance/ext/upbit.py
finance/ext/warehouse.py
finance/ext/profile/__init__.py
finance/ext/profile/base.py
finance/ext/profile/naver_finance.py
finance/ext/rapidapi/__init__.py
finance/ext/rapidapi/yahoo/__init__.py
finance/ext/rapidapi/yahoo/converter.py
finance/ext/rapidapi/yahoo/models.py
finance/ext/search/__init__.py
finance/ext/search/base.py
finance/ext/search/naver_finance.py
finance/providers/__init__.py
finance/providers/dart.py
finance/providers/kofia.py
finance/providers/miraeasset.py
finance/providers/provider.py
finance/providers/record.py
finance/providers/yahoo.py
sb_finance.egg-info/PKG-INFO
sb_finance.egg-info/SOURCES.txt
sb_finance.egg-info/dependency_links.txt
sb_finance.egg-info/entry_points.txt
sb_finance.egg-info/requires.txt
sb_finance.egg-info/top_level.txt