Metadata-Version: 2.1
Name: sb-finance
Version: 0.7.3
Summary: Personal Finance Project
Home-page: https://github.com/suminb/finance
Author: Sumin Byeon
Author-email: suminb@gmail.com
License: BSD
License-File: LICENSE
